AUTHORS
ChangeLog
LICENSE
README.rst
requirements.txt
setup.cfg
setup.py
coriolisclient/__init__.py
coriolisclient/base.py
coriolisclient/client.py
coriolisclient/constants.py
coriolisclient/exceptions.py
coriolisclient/version.py
coriolisclient/cli/__init__.py
coriolisclient/cli/formatter.py
coriolisclient/cli/migrations.py
coriolisclient/cli/shell.py
coriolisclient/v1/__init__.py
coriolisclient/v1/migrations.py
python_coriolisclient.egg-info/PKG-INFO
python_coriolisclient.egg-info/SOURCES.txt
python_coriolisclient.egg-info/dependency_links.txt
python_coriolisclient.egg-info/entry_points.txt
python_coriolisclient.egg-info/not-zip-safe
python_coriolisclient.egg-info/pbr.json
python_coriolisclient.egg-info/requires.txt
python_coriolisclient.egg-info/top_level.txt