Metadata-Version: 1.1
Name: python-coriolisclient
Version: 1.0.0.dev1
Summary: Coriolis Command-line Client
Home-page: http://cloudbase.it
Author: Cloudbase Solutions Srl
Author-email: info@cloudbasesolutions.com
License: UNKNOWN
Platform: UNKNOWN
Classifier: Intended Audience :: Information Technology
Classifier: Intended Audience :: System Administrators
Classifier: License :: OSI Approved :: Apache Software License
Classifier: Operating System :: POSIX :: Linux
Classifier: Programming Language :: Python
Classifier: Programming Language :: Python :: 2
Classifier: Programming Language :: Python :: 2.7
Classifier: Programming Language :: Python :: 3
Classifier: Programming Language :: Python :: 3.4
Classifier: Environment :: Console
